rich_demo/__init__.py
rich_demo/__main__.py
rich_demo-0.1.15.dist-info/METADATA
rich_demo-0.1.15.dist-info/WHEEL
rich_demo-0.1.15.dist-info/entry_points.txt
rich_demo-0.1.15.dist-info/RECORD
